noggin/__init__.py
noggin/app.py
noggin/controller/__init__.py
noggin/controller/authentication.py
noggin/controller/group.py
noggin/controller/password.py
noggin/controller/registration.py
noggin/controller/root.py
noggin/controller/user.py
noggin/defaults.py
noggin/form/__init__.py
noggin/form/base.py
noggin/form/edit_user.py
noggin/form/group.py
noggin/form/login_user.py
noggin/form/password_reset.py
noggin/form/register_user.py
noggin/form/sync_token.py
noggin/form/validators.py
noggin/l10n.py
noggin/middleware.py
noggin/representation/__init__.py
noggin/representation/agreement.py
noggin/representation/base.py
noggin/representation/group.py
noggin/representation/otptoken.py
noggin/representation/user.py
noggin/security/__init__.py
noggin/security/ipa.py
noggin/security/ipa_admin.py
noggin/signals.py
noggin/static/css/main.css
noggin/static/fonts/font-awesome/FontAwesome.otf
noggin/static/fonts/font-awesome/fontawesome-webfont.eot
noggin/static/fonts/font-awesome/fontawesome-webfont.svg
noggin/static/fonts/font-awesome/fontawesome-webfont.ttf
noggin/static/fonts/font-awesome/fontawesome-webfont.woff
noggin/static/fonts/font-awesome/fontawesome-webfont.woff2
noggin/static/fonts/font-awesome.css
noggin/static/js/search.js
noggin/static/js/vendor/corejs-typeahead-1.2.1/bloodhound.min.js
noggin/static/js/vendor/corejs-typeahead-1.2.1/typeahead.jquery.min.js
noggin/static/js/vendor/jquery-qrcode-1.0/MIT-LICENSE.txt
noggin/static/js/vendor/jquery-qrcode-1.0/README.md
noggin/static/js/vendor/jquery-qrcode-1.0/jquery.qrcode.min.js
noggin/static/js/vendor/jquery.dirty-0.7.2/LICENSE
noggin/static/js/vendor/jquery.dirty-0.7.2/README.md
noggin/static/js/vendor/jquery.dirty-0.7.2/jquery.dirty.js
noggin/static/js/vendor/moment-2.24.0/moment.js
noggin/static/js/vendor/moment-timezone-0.5.28-2019c/moment-timezone-with-data-10-year-range.js
noggin/static/js/vendor/selectize-0.12.6/selectize.bootstrap3.css
noggin/static/js/vendor/selectize-0.12.6/selectize.js
noggin_aaa-1.11.0.dist-info/METADATA
noggin_aaa-1.11.0.dist-info/WHEEL
noggin_aaa-1.11.0.dist-info/licenses/LICENSE
noggin_aaa-1.11.0.dist-info/RECORD
