Metadata-Version: 2.4
Name: noggin-aaa
Version: 1.11.0
Summary: Noggin is a self-service portal for FreeIPA. The primary purpose of the portal is to allow users to sign up and manage their account information and group membership.
License-Expression: MIT
License-File: LICENSE
Keywords: security
Author: Fedora Infrastructure
Author-email: admin@fedoraproject.org
Requires-Python: >=3.9.0,<4.0.0
Classifier: Environment :: Web Environment
Classifier: License :: OSI Approved :: MIT License
Classifier: Operating System :: POSIX :: Linux
Classifier: Programming Language :: Python :: 3
Classifier: Programming Language :: Python :: 3.9
Classifier: Programming Language :: Python :: 3.10
Classifier: Programming Language :: Python :: 3.11
Classifier: Programming Language :: Python :: 3.12
Classifier: Programming Language :: Python :: 3.13
Classifier: Programming Language :: Python :: 3.14
Classifier: Topic :: Internet :: WWW/HTTP :: Dynamic Content
Classifier: Topic :: System :: Systems Administration :: Authentication/Directory
Provides-Extra: deploy
Requires-Dist: Flask-Mail (>=0.9.1,<0.11.0)
Requires-Dist: backoff (>=1.6.0,<3.0)
Requires-Dist: click (>=8.0,<9.0)
Requires-Dist: cryptography (>=3.4.7)
Requires-Dist: fedora-messaging (>=2.1.0,<4.0)
Requires-Dist: flask (>=2.0.0,<4.0.0)
Requires-Dist: flask-babel (>=4.0.0,<5.0.0)
Requires-Dist: flask-healthz (>=1.0.0,<2.0.0)
Requires-Dist: flask-talisman (>=0.8.1,<2.0)
Requires-Dist: flask-wtf (>=0.14.3,<2.0.0)
Requires-Dist: gunicorn (>=20.0,<24.0.0) ; extra == "deploy"
Requires-Dist: markupsafe (>=1.1.1,<4.0.0)
Requires-Dist: noggin-messages (>=1.1.0,<2.0.0)
Requires-Dist: pyjwt (>=2.1.0,<3.0.0)
Requires-Dist: pyotp (>=2.2.7,<3.0.0)
Requires-Dist: python-freeipa (>=1.0.6,<2.0.0)
Requires-Dist: requests[security] (>=2.25.0,<3.0.0)
Requires-Dist: srvlookup (>=2.0.0,<4.0.0)
Requires-Dist: translitcodec (>=0.7.0)
Requires-Dist: unidecode (>=1.2.0,<2.0.0)
Requires-Dist: whitenoise (>=5.3,<7.0)
Requires-Dist: wtforms[email] (>=3.0.0,<4.0.0)
Project-URL: Homepage, https://github.com/fedora-infra/noggin
Project-URL: Repository, https://github.com/fedora-infra/noggin
